{
    "$schema": "vendor/infection/infection/resources/schema.json",
    "source": {
        "directories": [
            "src"
        ],
        "excludes": [
            "Photo/Infrastructure/Persistence/Doctrine/Entity"
        ]
    },
    "logs": {
        "text": "infection.log",
        "summary": "infection-summary.log"
    },
    "tmpDir": "var/cache/infection",
    "phpUnit": {
        "configDir": ".",
        "customPath": "vendor/bin/phpunit"
    },
    "testFramework": "phpunit",
    "testFrameworkOptions": "--configuration=phpunit-grumphp.xml.dist",
    "minMsi": 80,
    "minCoveredMsi": 90,
    "mutators": {
        "@default": true,
        "@function_signature": false
    },
    "bootstrap": "tests/bootstrap.php"
}
